pyaudiogame/__init__.py
pyaudiogame/app.py
pyaudiogame/console.py
pyaudiogame/event_handler.py
pyaudiogame/inputs.py
pyaudiogame/keymap.py
pyaudiogame/mixer.py
pyaudiogame/position.py
pyaudiogame/pygame_input.py
pyaudiogame/speech.py
pyaudiogame/storage.py
pyaudiogame/ticker.py
pyaudiogame/accessible_output2/__init__.py
pyaudiogame/accessible_output2/lib/PCTKUSR.dll
pyaudiogame/accessible_output2/lib/PCTKUSR64.dll
pyaudiogame/accessible_output2/lib/SAAPI32.dll
pyaudiogame/accessible_output2/lib/SAAPI64.dll
pyaudiogame/accessible_output2/lib/dolapi.dll
pyaudiogame/accessible_output2/lib/nvdaControllerClient32.dll
pyaudiogame/accessible_output2/lib/nvdaControllerClient64.dll
pyaudiogame/accessible_output2/libloader/__init__.py
pyaudiogame/accessible_output2/libloader/com.py
pyaudiogame/accessible_output2/libloader/libloader.py
pyaudiogame/accessible_output2/outputs/__init__.py
pyaudiogame/accessible_output2/outputs/auto.py
pyaudiogame/accessible_output2/outputs/base.py
pyaudiogame/accessible_output2/outputs/dolphin.py
pyaudiogame/accessible_output2/outputs/e_speak.py
pyaudiogame/accessible_output2/outputs/jaws.py
pyaudiogame/accessible_output2/outputs/nvda.py
pyaudiogame/accessible_output2/outputs/pc_talker.py
pyaudiogame/accessible_output2/outputs/sapi4.py
pyaudiogame/accessible_output2/outputs/sapi5.py
pyaudiogame/accessible_output2/outputs/say.py
pyaudiogame/accessible_output2/outputs/system_access.py
pyaudiogame/accessible_output2/outputs/voiceover.py
pyaudiogame/accessible_output2/outputs/window_eyes.py
pyaudiogame/accessible_output2/platform_utils/__init__.py
pyaudiogame/accessible_output2/platform_utils/blackhole.py
pyaudiogame/accessible_output2/platform_utils/clipboard.py
pyaudiogame/accessible_output2/platform_utils/libloader.py
pyaudiogame/accessible_output2/platform_utils/paths.py
pyaudiogame/accessible_output2/platform_utils/autostart/__init__.py
pyaudiogame/accessible_output2/platform_utils/autostart/windows.py
pyaudiogame-0.0.3.dist-info/LICENSE.txt
pyaudiogame-0.0.3.dist-info/METADATA
pyaudiogame-0.0.3.dist-info/WHEEL
pyaudiogame-0.0.3.dist-info/top_level.txt
pyaudiogame-0.0.3.dist-info/RECORD
